setup.cfg
setup.py
py_salesforce/__init__.py
py_salesforce/py_salesforce.conf
py_salesforce/py_salesforce.py
py_salesforce.egg-info/PKG-INFO
py_salesforce.egg-info/SOURCES.txt
py_salesforce.egg-info/dependency_links.txt
py_salesforce.egg-info/requires.txt
py_salesforce.egg-info/top_level.txt